[{"displayName":"Language","name":"Language","id":"Language","type":"feature","path":"","narrative":{"name":"Narrative","text":""},"children":[{"displayName":"Language test","name":"Language test","id":"Language test","type":"story","path":"language","narrative":{"name":"Narrative","text":""},"parent":"Language","scenarioTags":{},"containsNoScenarios":false}],"scenarioTags":{},"containsNoScenarios":false},{"displayName":"Search","name":"Search","id":"Search","type":"feature","path":"","narrative":{"name":"Narrative","text":""},"children":[{"displayName":"Search product test","name":"Search product test","id":"Search product test","type":"story","path":"search","narrative":{"name":"Narrative","text":""},"parent":"Search","scenarioTags":{},"containsNoScenarios":false}],"scenarioTags":{},"containsNoScenarios":false},{"displayName":"Sort","name":"Sort","id":"Sort","type":"feature","path":"","narrative":{"name":"Narrative","text":""},"children":[{"displayName":"Sort test","name":"Sort test","id":"Sort test","type":"story","path":"sort","narrative":{"name":"Narrative","text":""},"parent":"Sort","scenarioTags":{},"containsNoScenarios":false}],"scenarioTags":{},"containsNoScenarios":false}]