{"name":"get_page_title","id":"atstUIAutomation.features.search.RNTest:get_page_title","testCaseName":"atstUIAutomation.features.search.RNTest","testSteps":[{"number":1,"description":"Get page title","duration":20009,"startTime":"2021-10-25T12:32:17.907440900+03:00[Europe/Athens]","screenshots":[{"screenshot":"387958dc96404e778b1ad28ad933eb0ddb6c06a5c35713221199c834fb3782d7.png","timeStamp":1635154357917}],"result":"SUCCESS","precondition":false,"level":0}],"userStory":{"id":"atstUIAutomation.features.search.RNTest","storyName":"RN test","storyClassName":"atstUIAutomation.features.search.RNTest","path":"search","type":"story"},"featureTag":{"name":"Search/RN test","type":"story","displayName":"Search/RN test"},"title":"Get page title","tags":[{"name":"Search/RN test","type":"story","displayName":"RN test"},{"name":"Search","type":"feature","displayName":"Search"},{"name":"Search","type":"capability","displayName":"Search for definitions"}],"startTime":"2021-10-25T12:32:17.645101500+03:00[Europe/Athens]","duration":20272,"projectKey":"","sessionId":"ea8922908b2804be3cb9caf43ccbdce5","driver":"chrome","isManualTestingUpToDate":false,"manual":false,"testSource":"JUnit","order":0,"result":"SUCCESS"}